{
  "zonesCrossNominees": [
    [],
    [
      {
        "inZone": [
          true,
          false
        ],
        "crossingPair": [
          {
            "time": "2014-01-03T03:28:13Z",
            "lat": -33.4427,
            "fix": 2514,
            "lng": 147.9775,
            "alt": 1980
          },
          {
            "time": "2014-01-03T03:28:14Z",
            "lat": -33.442783,
            "fix": 2515,
            "lng": 147.977667,
            "alt": 1979
          }
        ]
      },
      {
        "inZone": [
          false,
          true
        ],
        "crossingPair": [
          {
            "time": "2014-01-03T03:28:24Z",
            "lat": -33.442267,
            "fix": 2525,
            "lng": 147.978967,
            "alt": 1977
          },
          {
            "time": "2014-01-03T03:28:25Z",
            "lat": -33.44215,
            "fix": 2526,
            "lng": 147.978933,
            "alt": 1976
          }
        ]
      },
      {
        "inZone": [
          true,
          false
        ],
        "crossingPair": [
          {
            "time": "2014-01-03T03:30:13Z",
            "lat": -33.444633,
            "fix": 2634,
            "lng": 147.972033,
            "alt": 1812
          },
          {
            "time": "2014-01-03T03:30:14Z",
            "lat": -33.444767,
            "fix": 2635,
            "lng": 147.972133,
            "alt": 1810
          }
        ]
      }
    ],
    [],
    []
  ],
  "zonesCrossExcluded": [],
  "startSelected": [
    "2014-01-03T03:30:00Z",
    {
      "inZone": [
        true,
        false
      ],
      "crossingPair": [
        {
          "time": "2014-01-03T03:30:13Z",
          "lat": -33.444633,
          "fix": 2634,
          "lng": 147.972033,
          "alt": 1812
        },
        {
          "time": "2014-01-03T03:30:14Z",
          "lat": -33.444767,
          "fix": 2635,
          "lng": 147.972133,
          "alt": 1810
        }
      ]
    }
  ],
  "zonesCrossSelected": [
    null,
    {
      "inZone": [
        true,
        false
      ],
      "crossingPair": [
        {
          "time": "2014-01-03T03:30:13Z",
          "lat": -33.444633,
          "fix": 2634,
          "lng": 147.972033,
          "alt": 1812
        },
        {
          "time": "2014-01-03T03:30:14Z",
          "lat": -33.444767,
          "fix": 2635,
          "lng": 147.972133,
          "alt": 1810
        }
      ]
    },
    null,
    null
  ],
  "startNominees": [
    [
      "2014-01-03T03:30:00Z",
      [
        {
          "inZone": [
            true,
            false
          ],
          "crossingPair": [
            {
              "time": "2014-01-03T03:30:13Z",
              "lat": -33.444633,
              "fix": 2634,
              "lng": 147.972033,
              "alt": 1812
            },
            {
              "time": "2014-01-03T03:30:14Z",
              "lat": -33.444767,
              "fix": 2635,
              "lng": 147.972133,
              "alt": 1810
            }
          ]
        }
      ]
    ],
    [
      "2014-01-03T03:00:00Z",
      [
        {
          "inZone": [
            true,
            false
          ],
          "crossingPair": [
            {
              "time": "2014-01-03T03:28:13Z",
              "lat": -33.4427,
              "fix": 2514,
              "lng": 147.9775,
              "alt": 1980
            },
            {
              "time": "2014-01-03T03:28:14Z",
              "lat": -33.442783,
              "fix": 2515,
              "lng": 147.977667,
              "alt": 1979
            }
          ]
        }
      ]
    ]
  ]
}
