{
  "zonesCrossNominees": [
    [
      {
        "inZone": [
          false,
          true
        ],
        "crossingPair": [
          {
            "time": "2013-12-31T02:37:43Z",
            "lat": -33.35698,
            "fix": 614,
            "lng": 147.932499,
            "alt": 279
          },
          {
            "time": "2013-12-31T02:37:48Z",
            "lat": -33.35739,
            "fix": 615,
            "lng": 147.93203,
            "alt": 293
          }
        ]
      },
      {
        "inZone": [
          true,
          false
        ],
        "crossingPair": [
          {
            "time": "2013-12-31T02:38:28Z",
            "lat": -33.359776,
            "fix": 623,
            "lng": 147.927881,
            "alt": 402
          },
          {
            "time": "2013-12-31T02:38:33Z",
            "lat": -33.359906,
            "fix": 624,
            "lng": 147.927276,
            "alt": 421
          }
        ]
      }
    ],
    [
      {
        "inZone": [
          true,
          false
        ],
        "crossingPair": [
          {
            "time": "2013-12-31T03:13:34Z",
            "lat": -33.286656,
            "fix": 1044,
            "lng": 147.993415,
            "alt": 862
          },
          {
            "time": "2013-12-31T03:13:39Z",
            "lat": -33.28582,
            "fix": 1045,
            "lng": 147.994157,
            "alt": 873
          }
        ]
      },
      {
        "inZone": [
          false,
          true
        ],
        "crossingPair": [
          {
            "time": "2013-12-31T03:28:05Z",
            "lat": -33.287068,
            "fix": 1218,
            "lng": 147.995104,
            "alt": 1822
          },
          {
            "time": "2013-12-31T03:28:10Z",
            "lat": -33.287578,
            "fix": 1219,
            "lng": 147.994539,
            "alt": 1812
          }
        ]
      },
      {
        "inZone": [
          true,
          false
        ],
        "crossingPair": [
          {
            "time": "2013-12-31T03:38:10Z",
            "lat": -33.28471,
            "fix": 1339,
            "lng": 147.989318,
            "alt": 1543
          },
          {
            "time": "2013-12-31T03:38:15Z",
            "lat": -33.283956,
            "fix": 1340,
            "lng": 147.989932,
            "alt": 1532
          }
        ]
      }
    ],
    [
      {
        "inZone": [
          false,
          true
        ],
        "crossingPair": [
          {
            "time": "2013-12-31T05:11:06Z",
            "lat": -32.801956,
            "fix": 2454,
            "lng": 148.626342,
            "alt": 2134
          },
          {
            "time": "2013-12-31T05:11:11Z",
            "lat": -32.801723,
            "fix": 2455,
            "lng": 148.627517,
            "alt": 2132
          }
        ]
      },
      {
        "inZone": [
          true,
          false
        ],
        "crossingPair": [
          {
            "time": "2013-12-31T05:16:56Z",
            "lat": -32.803522,
            "fix": 2524,
            "lng": 148.664153,
            "alt": 2672
          },
          {
            "time": "2013-12-31T05:17:01Z",
            "lat": -32.80397,
            "fix": 2525,
            "lng": 148.664824,
            "alt": 2670
          }
        ]
      }
    ],
    [
      {
        "inZone": [
          false,
          true
        ],
        "crossingPair": [
          {
            "time": "2013-12-31T05:29:26Z",
            "lat": -32.894177,
            "fix": 2674,
            "lng": 148.726906,
            "alt": 1075
          },
          {
            "time": "2013-12-31T05:29:31Z",
            "lat": -32.894823,
            "fix": 2675,
            "lng": 148.727373,
            "alt": 1060
          }
        ]
      },
      {
        "inZone": [
          true,
          false
        ],
        "crossingPair": [
          {
            "time": "2013-12-31T05:29:51Z",
            "lat": -32.892876,
            "fix": 2679,
            "lng": 148.731044,
            "alt": 1012
          },
          {
            "time": "2013-12-31T05:29:56Z",
            "lat": -32.891959,
            "fix": 2680,
            "lng": 148.731772,
            "alt": 1002
          }
        ]
      }
    ],
    []
  ],
  "zonesCrossExcluded": [],
  "startSelected": [
    "2013-12-31T03:35:00Z",
    {
      "inZone": [
        true,
        false
      ],
      "crossingPair": [
        {
          "time": "2013-12-31T03:38:10Z",
          "lat": -33.28471,
          "fix": 1339,
          "lng": 147.989318,
          "alt": 1543
        },
        {
          "time": "2013-12-31T03:38:15Z",
          "lat": -33.283956,
          "fix": 1340,
          "lng": 147.989932,
          "alt": 1532
        }
      ]
    }
  ],
  "zonesCrossSelected": [
    {
      "inZone": [
        false,
        true
      ],
      "crossingPair": [
        {
          "time": "2013-12-31T02:37:43Z",
          "lat": -33.35698,
          "fix": 614,
          "lng": 147.932499,
          "alt": 279
        },
        {
          "time": "2013-12-31T02:37:48Z",
          "lat": -33.35739,
          "fix": 615,
          "lng": 147.93203,
          "alt": 293
        }
      ]
    },
    {
      "inZone": [
        true,
        false
      ],
      "crossingPair": [
        {
          "time": "2013-12-31T03:38:10Z",
          "lat": -33.28471,
          "fix": 1339,
          "lng": 147.989318,
          "alt": 1543
        },
        {
          "time": "2013-12-31T03:38:15Z",
          "lat": -33.283956,
          "fix": 1340,
          "lng": 147.989932,
          "alt": 1532
        }
      ]
    },
    {
      "inZone": [
        false,
        true
      ],
      "crossingPair": [
        {
          "time": "2013-12-31T05:11:06Z",
          "lat": -32.801956,
          "fix": 2454,
          "lng": 148.626342,
          "alt": 2134
        },
        {
          "time": "2013-12-31T05:11:11Z",
          "lat": -32.801723,
          "fix": 2455,
          "lng": 148.627517,
          "alt": 2132
        }
      ]
    },
    {
      "inZone": [
        false,
        true
      ],
      "crossingPair": [
        {
          "time": "2013-12-31T05:29:26Z",
          "lat": -32.894177,
          "fix": 2674,
          "lng": 148.726906,
          "alt": 1075
        },
        {
          "time": "2013-12-31T05:29:31Z",
          "lat": -32.894823,
          "fix": 2675,
          "lng": 148.727373,
          "alt": 1060
        }
      ]
    },
    null
  ],
  "startNominees": [
    [
      "2013-12-31T03:55:00Z",
      []
    ],
    [
      "2013-12-31T03:35:00Z",
      [
        {
          "inZone": [
            true,
            false
          ],
          "crossingPair": [
            {
              "time": "2013-12-31T03:38:10Z",
              "lat": -33.28471,
              "fix": 1339,
              "lng": 147.989318,
              "alt": 1543
            },
            {
              "time": "2013-12-31T03:38:15Z",
              "lat": -33.283956,
              "fix": 1340,
              "lng": 147.989932,
              "alt": 1532
            }
          ]
        }
      ]
    ],
    [
      "2013-12-31T03:15:00Z",
      []
    ]
  ]
}
