[
  [
    [
      "39",
      "Jonny Durand"
    ],
    {
      "area": "1159929.6462 km^2 s",
      "frac": 1,
      "coef": 3.31999834
    }
  ],
  [
    [
      "70",
      "Carl Wallbank"
    ],
    {
      "area": "1170914.3615 km^2 s",
      "frac": 0.93322446,
      "coef": 3.35143924
    }
  ],
  [
    [
      "62",
      "Christian Voiblet"
    ],
    {
      "area": "1187891.1390 km^2 s",
      "frac": 0.87551078,
      "coef": 3.40003087
    }
  ],
  [
    [
      "23",
      "Anton Struganov"
    ],
    {
      "area": "1188377.6946 km^2 s",
      "frac": 0.87407078,
      "coef": 3.40142351
    }
  ],
  [
    [
      "33",
      "Filippo Oppici"
    ],
    {
      "area": "1188945.2633 km^2 s",
      "frac": 0.87240135,
      "coef": 3.40304803
    }
  ],
  [
    [
      "34",
      "Glen Mcfarlane"
    ],
    {
      "area": "1190212.3672 km^2 s",
      "frac": 0.86871308,
      "coef": 3.40667479
    }
  ],
  [
    [
      "41",
      "Attila Bertok"
    ],
    {
      "area": "1198714.9669 km^2 s",
      "frac": 0.84516477,
      "coef": 3.43101128
    }
  ],
  [
    [
      "45",
      "Geoff Robertson"
    ],
    {
      "area": "1242631.5622 km^2 s",
      "frac": 0.74349142,
      "coef": 3.55671116
    }
  ],
  [
    [
      "24",
      "Steve Blenkinsop"
    ],
    {
      "area": "1438575.4410 km^2 s",
      "frac": 0.42350813,
      "coef": 4.11754979
    }
  ],
  [
    [
      "46",
      "Yasuhiro Noma"
    ],
    {
      "area": "1453378.7903 km^2 s",
      "frac": 0.40326696,
      "coef": 4.15992054
    }
  ],
  [
    [
      "1",
      "Michael Bilyk"
    ],
    {
      "area": "1455860.9211 km^2 s",
      "frac": 0.39990672,
      "coef": 4.167025
    }
  ],
  [
    [
      "3",
      "Paris Williams"
    ],
    {
      "area": "1457752.0620 km^2 s",
      "frac": 0.39735284,
      "coef": 4.1724379
    }
  ],
  [
    [
      "55",
      "Len Paton"
    ],
    {
      "area": "1462072.7836 km^2 s",
      "frac": 0.39153816,
      "coef": 4.18480485
    }
  ],
  [
    [
      "49",
      "Jonas Lobitz"
    ],
    {
      "area": "1465102.5169 km^2 s",
      "frac": 0.38747737,
      "coef": 4.19347668
    }
  ],
  [
    [
      "40",
      "Lukas Bader"
    ],
    {
      "area": "1467338.6673 km^2 s",
      "frac": 0.38448884,
      "coef": 4.19987708
    }
  ],
  [
    [
      "51",
      "Gavin Myers"
    ],
    {
      "area": "1470777.0717 km^2 s",
      "frac": 0.37990765,
      "coef": 4.20971862
    }
  ],
  [
    [
      "60",
      "Davis Straub"
    ],
    {
      "area": "1522519.8636 km^2 s",
      "frac": 0.31287527,
      "coef": 4.35781897
    }
  ],
  [
    [
      "42",
      "Trent Brown"
    ],
    {
      "area": "1617280.6759 km^2 s",
      "frac": 0.19784561,
      "coef": 4.62904726
    }
  ],
  [
    [
      "30",
      "Phil Schroder"
    ],
    {
      "area": "1642272.7762 km^2 s",
      "frac": 0.16888283,
      "coef": 4.70058068
    }
  ],
  [
    [
      "7",
      "Tony Giammichele"
    ],
    {
      "area": "1715194.4230 km^2 s",
      "frac": 0.08709636,
      "coef": 4.90930002
    }
  ],
  [
    [
      "50",
      "Conrad Loten"
    ],
    {
      "area": "1821648.1114 km^2 s",
      "frac": 0,
      "coef": 5.21399614
    }
  ],
  [
    [
      "43",
      "Rod Flockhart"
    ],
    {
      "area": "1844106.4315 km^2 s",
      "frac": 0,
      "coef": 5.27827727
    }
  ],
  [
    [
      "20",
      "Nils Vesk"
    ],
    {
      "area": "1845240.7996 km^2 s",
      "frac": 0,
      "coef": 5.2815241
    }
  ],
  [
    [
      "44",
      "Patrick Collin"
    ],
    {
      "area": "1864513.3701 km^2 s",
      "frac": 0,
      "coef": 5.33668685
    }
  ],
  [
    [
      "52",
      "Olav Olsen"
    ],
    {
      "area": "2255972.9834 km^2 s",
      "frac": 0,
      "coef": 6.45713865
    }
  ],
  [
    [
      "28",
      "Guy Hubbard"
    ],
    {
      "area": "2468425.1551 km^2 s",
      "frac": 0,
      "coef": 7.06522799
    }
  ],
  [
    [
      "29",
      "Adam Stevens"
    ],
    {
      "area": "2517055.3486 km^2 s",
      "frac": 0,
      "coef": 7.20441933
    }
  ],
  [
    [
      "31",
      "Dean Hervatin"
    ],
    {
      "area": "2711780.6889 km^2 s",
      "frac": 0,
      "coef": 7.76177021
    }
  ]
]
