{
  "zonesCrossNominees": [
    [
      {
        "inZone": [
          false,
          true
        ],
        "crossingPair": [
          {
            "time": "2013-12-28T02:51:53Z",
            "lat": -33.357247,
            "fix": 447,
            "lng": 147.930911,
            "alt": 1062
          },
          {
            "time": "2013-12-28T02:51:55Z",
            "lat": -33.357419,
            "fix": 448,
            "lng": 147.930679,
            "alt": 1060
          }
        ]
      },
      {
        "inZone": [
          true,
          false
        ],
        "crossingPair": [
          {
            "time": "2013-12-28T02:51:58Z",
            "lat": -33.357534,
            "fix": 449,
            "lng": 147.930277,
            "alt": 1068
          },
          {
            "time": "2013-12-28T02:52:01Z",
            "lat": -33.357456,
            "fix": 450,
            "lng": 147.929961,
            "alt": 1073
          }
        ]
      },
      {
        "inZone": [
          false,
          true
        ],
        "crossingPair": [
          {
            "time": "2013-12-28T02:52:13Z",
            "lat": -33.356858,
            "fix": 455,
            "lng": 147.931221,
            "alt": 1083
          },
          {
            "time": "2013-12-28T02:52:17Z",
            "lat": -33.357317,
            "fix": 456,
            "lng": 147.931237,
            "alt": 1085
          }
        ]
      },
      {
        "inZone": [
          true,
          false
        ],
        "crossingPair": [
          {
            "time": "2013-12-28T02:52:22Z",
            "lat": -33.357415,
            "fix": 459,
            "lng": 147.930685,
            "alt": 1095
          },
          {
            "time": "2013-12-28T02:52:24Z",
            "lat": -33.357382,
            "fix": 460,
            "lng": 147.930496,
            "alt": 1096
          }
        ]
      },
      {
        "inZone": [
          false,
          true
        ],
        "crossingPair": [
          {
            "time": "2013-12-28T02:52:43Z",
            "lat": -33.357092,
            "fix": 467,
            "lng": 147.932074,
            "alt": 1116
          },
          {
            "time": "2013-12-28T02:52:47Z",
            "lat": -33.357608,
            "fix": 468,
            "lng": 147.932113,
            "alt": 1121
          }
        ]
      },
      {
        "inZone": [
          true,
          false
        ],
        "crossingPair": [
          {
            "time": "2013-12-28T02:53:04Z",
            "lat": -33.357241,
            "fix": 475,
            "lng": 147.931324,
            "alt": 1129
          },
          {
            "time": "2013-12-28T02:53:07Z",
            "lat": -33.356797,
            "fix": 476,
            "lng": 147.931493,
            "alt": 1132
          }
        ]
      },
      {
        "inZone": [
          false,
          true
        ],
        "crossingPair": [
          {
            "time": "2013-12-28T02:53:25Z",
            "lat": -33.357297,
            "fix": 484,
            "lng": 147.933661,
            "alt": 1155
          },
          {
            "time": "2013-12-28T02:53:27Z",
            "lat": -33.357559,
            "fix": 485,
            "lng": 147.933533,
            "alt": 1159
          }
        ]
      },
      {
        "inZone": [
          true,
          false
        ],
        "crossingPair": [
          {
            "time": "2013-12-28T02:53:33Z",
            "lat": -33.357599,
            "fix": 488,
            "lng": 147.932891,
            "alt": 1167
          },
          {
            "time": "2013-12-28T02:53:36Z",
            "lat": -33.357194,
            "fix": 489,
            "lng": 147.93295,
            "alt": 1169
          }
        ]
      },
      {
        "inZone": [
          false,
          true
        ],
        "crossingPair": [
          {
            "time": "2013-12-28T02:53:45Z",
            "lat": -33.357494,
            "fix": 493,
            "lng": 147.934174,
            "alt": 1180
          },
          {
            "time": "2013-12-28T02:53:49Z",
            "lat": -33.357966,
            "fix": 494,
            "lng": 147.933904,
            "alt": 1182
          }
        ]
      },
      {
        "inZone": [
          true,
          false
        ],
        "crossingPair": [
          {
            "time": "2013-12-28T02:53:56Z",
            "lat": -33.357538,
            "fix": 497,
            "lng": 147.933255,
            "alt": 1193
          },
          {
            "time": "2013-12-28T02:53:59Z",
            "lat": -33.357215,
            "fix": 498,
            "lng": 147.933443,
            "alt": 1196
          }
        ]
      },
      {
        "inZone": [
          false,
          true
        ],
        "crossingPair": [
          {
            "time": "2013-12-28T02:54:14Z",
            "lat": -33.358038,
            "fix": 504,
            "lng": 147.935045,
            "alt": 1204
          },
          {
            "time": "2013-12-28T02:54:16Z",
            "lat": -33.358224,
            "fix": 505,
            "lng": 147.934868,
            "alt": 1207
          }
        ]
      },
      {
        "inZone": [
          true,
          false
        ],
        "crossingPair": [
          {
            "time": "2013-12-28T02:54:41Z",
            "lat": -33.357245,
            "fix": 515,
            "lng": 147.932266,
            "alt": 1225
          },
          {
            "time": "2013-12-28T02:54:43Z",
            "lat": -33.357024,
            "fix": 516,
            "lng": 147.932128,
            "alt": 1227
          }
        ]
      },
      {
        "inZone": [
          false,
          true
        ],
        "crossingPair": [
          {
            "time": "2013-12-28T02:55:10Z",
            "lat": -33.356999,
            "fix": 533,
            "lng": 147.932909,
            "alt": 1309
          },
          {
            "time": "2013-12-28T02:55:13Z",
            "lat": -33.357324,
            "fix": 534,
            "lng": 147.932671,
            "alt": 1323
          }
        ]
      },
      {
        "inZone": [
          true,
          false
        ],
        "crossingPair": [
          {
            "time": "2013-12-28T02:55:38Z",
            "lat": -33.358246,
            "fix": 546,
            "lng": 147.933174,
            "alt": 1386
          },
          {
            "time": "2013-12-28T02:55:42Z",
            "lat": -33.357101,
            "fix": 547,
            "lng": 147.933857,
            "alt": 1400
          }
        ]
      },
      {
        "inZone": [
          false,
          true
        ],
        "crossingPair": [
          {
            "time": "2013-12-28T02:55:44Z",
            "lat": -33.357358,
            "fix": 548,
            "lng": 147.934162,
            "alt": 1403
          },
          {
            "time": "2013-12-28T02:55:47Z",
            "lat": -33.357875,
            "fix": 549,
            "lng": 147.934325,
            "alt": 1408
          }
        ]
      },
      {
        "inZone": [
          true,
          false
        ],
        "crossingPair": [
          {
            "time": "2013-12-28T02:55:56Z",
            "lat": -33.357753,
            "fix": 555,
            "lng": 147.933703,
            "alt": 1430
          },
          {
            "time": "2013-12-28T02:55:58Z",
            "lat": -33.357528,
            "fix": 556,
            "lng": 147.933948,
            "alt": 1433
          }
        ]
      },
      {
        "inZone": [
          false,
          true
        ],
        "crossingPair": [
          {
            "time": "2013-12-28T02:56:09Z",
            "lat": -33.358206,
            "fix": 562,
            "lng": 147.935282,
            "alt": 1461
          },
          {
            "time": "2013-12-28T02:56:13Z",
            "lat": -33.358402,
            "fix": 563,
            "lng": 147.934861,
            "alt": 1461
          }
        ]
      },
      {
        "inZone": [
          true,
          false
        ],
        "crossingPair": [
          {
            "time": "2013-12-28T02:56:22Z",
            "lat": -33.357627,
            "fix": 567,
            "lng": 147.93401,
            "alt": 1482
          },
          {
            "time": "2013-12-28T02:56:23Z",
            "lat": -33.357516,
            "fix": 568,
            "lng": 147.933964,
            "alt": 1487
          }
        ]
      }
    ],
    [
      {
        "inZone": [
          true,
          false
        ],
        "crossingPair": [
          {
            "time": "2013-12-28T03:07:11Z",
            "lat": -33.397725,
            "fix": 838,
            "lng": 147.962903,
            "alt": 1732
          },
          {
            "time": "2013-12-28T03:07:12Z",
            "lat": -33.397861,
            "fix": 839,
            "lng": 147.962985,
            "alt": 1732
          }
        ]
      }
    ],
    [
      {
        "inZone": [
          false,
          true
        ],
        "crossingPair": [
          {
            "time": "2013-12-28T05:02:06Z",
            "lat": -33.85758,
            "fix": 4114,
            "lng": 148.108393,
            "alt": 1450
          },
          {
            "time": "2013-12-28T05:02:08Z",
            "lat": -33.857845,
            "fix": 4115,
            "lng": 148.108353,
            "alt": 1446
          }
        ]
      },
      {
        "inZone": [
          true,
          false
        ],
        "crossingPair": [
          {
            "time": "2013-12-28T05:03:21Z",
            "lat": -33.856872,
            "fix": 4156,
            "lng": 148.114478,
            "alt": 1235
          },
          {
            "time": "2013-12-28T05:03:23Z",
            "lat": -33.856587,
            "fix": 4157,
            "lng": 148.114569,
            "alt": 1232
          }
        ]
      }
    ],
    [],
    [],
    []
  ],
  "zonesCrossExcluded": [],
  "startSelected": [
    "2013-12-28T03:00:00Z",
    {
      "inZone": [
        true,
        false
      ],
      "crossingPair": [
        {
          "time": "2013-12-28T03:07:11Z",
          "lat": -33.397725,
          "fix": 838,
          "lng": 147.962903,
          "alt": 1732
        },
        {
          "time": "2013-12-28T03:07:12Z",
          "lat": -33.397861,
          "fix": 839,
          "lng": 147.962985,
          "alt": 1732
        }
      ]
    }
  ],
  "zonesCrossSelected": [
    {
      "inZone": [
        false,
        true
      ],
      "crossingPair": [
        {
          "time": "2013-12-28T02:51:53Z",
          "lat": -33.357247,
          "fix": 447,
          "lng": 147.930911,
          "alt": 1062
        },
        {
          "time": "2013-12-28T02:51:55Z",
          "lat": -33.357419,
          "fix": 448,
          "lng": 147.930679,
          "alt": 1060
        }
      ]
    },
    {
      "inZone": [
        true,
        false
      ],
      "crossingPair": [
        {
          "time": "2013-12-28T03:07:11Z",
          "lat": -33.397725,
          "fix": 838,
          "lng": 147.962903,
          "alt": 1732
        },
        {
          "time": "2013-12-28T03:07:12Z",
          "lat": -33.397861,
          "fix": 839,
          "lng": 147.962985,
          "alt": 1732
        }
      ]
    },
    {
      "inZone": [
        false,
        true
      ],
      "crossingPair": [
        {
          "time": "2013-12-28T05:02:06Z",
          "lat": -33.85758,
          "fix": 4114,
          "lng": 148.108393,
          "alt": 1450
        },
        {
          "time": "2013-12-28T05:02:08Z",
          "lat": -33.857845,
          "fix": 4115,
          "lng": 148.108353,
          "alt": 1446
        }
      ]
    },
    null,
    null,
    null
  ],
  "startNominees": [
    [
      "2013-12-28T03:40:00Z",
      []
    ],
    [
      "2013-12-28T03:20:00Z",
      []
    ],
    [
      "2013-12-28T03:00:00Z",
      [
        {
          "inZone": [
            true,
            false
          ],
          "crossingPair": [
            {
              "time": "2013-12-28T03:07:11Z",
              "lat": -33.397725,
              "fix": 838,
              "lng": 147.962903,
              "alt": 1732
            },
            {
              "time": "2013-12-28T03:07:12Z",
              "lat": -33.397861,
              "fix": 839,
              "lng": 147.962985,
              "alt": 1732
            }
          ]
        }
      ]
    ]
  ]
}
