[
  {
    "inter": {
      "time": "2013-12-31T02:17:29.205827918734Z",
      "lat": -33.35748349,
      "fixFrac": 32.40194263957857,
      "lng": 147.93372295,
      "alt": 261.41
    },
    "cross": {
      "inZone": [
        false,
        true
      ],
      "crossingPair": [
        {
          "time": "2013-12-31T02:17:28Z",
          "lat": -33.357383,
          "fix": 32,
          "lng": 147.933817,
          "alt": 259
        },
        {
          "time": "2013-12-31T02:17:31Z",
          "lat": -33.357633,
          "fix": 33,
          "lng": 147.933583,
          "alt": 265
        }
      ]
    }
  },
  {
    "inter": {
      "time": "2013-12-31T03:35:22.357156174916Z",
      "lat": -33.27357764,
      "fixFrac": 1589.7857187249722,
      "lng": 147.96034736,
      "alt": 1500.64
    },
    "cross": {
      "inZone": [
        true,
        false
      ],
      "crossingPair": [
        {
          "time": "2013-12-31T03:35:20Z",
          "lat": -33.2738,
          "fix": 1589,
          "lng": 147.95985,
          "alt": 1503
        },
        {
          "time": "2013-12-31T03:35:23Z",
          "lat": -33.273517,
          "fix": 1590,
          "lng": 147.960483,
          "alt": 1500
        }
      ]
    }
  },
  {
    "inter": {
      "time": "2013-12-31T05:02:43.037908441661Z",
      "lat": -32.80530877,
      "fixFrac": 3334.0379084416613,
      "lng": 148.6567349,
      "alt": 2693.96
    },
    "cross": {
      "inZone": [
        false,
        true
      ],
      "crossingPair": [
        {
          "time": "2013-12-31T05:02:43Z",
          "lat": -32.805317,
          "fix": 3334,
          "lng": 148.656733,
          "alt": 2694
        },
        {
          "time": "2013-12-31T05:02:44Z",
          "lat": -32.8051,
          "fix": 3335,
          "lng": 148.656783,
          "alt": 2693
        }
      ]
    }
  },
  {
    "inter": {
      "time": "2013-12-31T05:21:27.869033146408Z",
      "lat": -32.89183692,
      "fixFrac": 3709.956344382137,
      "lng": 148.73432137,
      "alt": 1171.13
    },
    "cross": {
      "inZone": [
        false,
        true
      ],
      "crossingPair": [
        {
          "time": "2013-12-31T05:21:25Z",
          "lat": -32.89155,
          "fix": 3709,
          "lng": 148.734067,
          "alt": 1174
        },
        {
          "time": "2013-12-31T05:21:28Z",
          "lat": -32.89185,
          "fix": 3710,
          "lng": 148.734333,
          "alt": 1171
        }
      ]
    }
  },
  {
    "inter": {
      "time": "2013-12-31T06:12:35.927395344477Z",
      "lat": -32.46648474,
      "fixFrac": 4732.975798448159,
      "lng": 148.98591727,
      "alt": 589.24
    },
    "cross": {
      "inZone": [
        false,
        true
      ],
      "crossingPair": [
        {
          "time": "2013-12-31T06:12:33Z",
          "lat": -32.4672,
          "fix": 4732,
          "lng": 148.985283,
          "alt": 599
        },
        {
          "time": "2013-12-31T06:12:36Z",
          "lat": -32.466467,
          "fix": 4733,
          "lng": 148.985933,
          "alt": 589
        }
      ]
    }
  }
]
