[
  {
    "inter": {
      "time": "2013-12-31T02:59:59.674854276844Z",
      "lat": -33.35747148,
      "fixFrac": 1138.3374271384225,
      "lng": 147.93368945,
      "alt": 216.67
    },
    "cross": {
      "inZone": [
        false,
        true
      ],
      "crossingPair": [
        {
          "time": "2013-12-31T02:59:59Z",
          "lat": -33.357404,
          "fix": 1138,
          "lng": 147.933735,
          "alt": 216
        },
        {
          "time": "2013-12-31T03:00:01Z",
          "lat": -33.357604,
          "fix": 1139,
          "lng": 147.9336,
          "alt": 218
        }
      ]
    }
  },
  {
    "inter": {
      "time": "2013-12-31T03:25:05.241903320714Z",
      "lat": -33.28022048,
      "fixFrac": 1890.1209516603578,
      "lng": 147.98099018,
      "alt": 1193.88
    },
    "cross": {
      "inZone": [
        true,
        false
      ],
      "crossingPair": [
        {
          "time": "2013-12-31T03:25:05Z",
          "lat": -33.280261,
          "fix": 1890,
          "lng": 147.980995,
          "alt": 1194
        },
        {
          "time": "2013-12-31T03:25:07Z",
          "lat": -33.279926,
          "fix": 1891,
          "lng": 147.980955,
          "alt": 1193
        }
      ]
    }
  },
  null,
  null,
  null
]
